ml_ms4alg/__init__.py
ml_ms4alg/compute_noise_overlap.py
ml_ms4alg/curation.py
ml_ms4alg/curation_spec.py.mp
ml_ms4alg/mountainsort4.py
ml_ms4alg/mountainsort4_curation.py
ml_ms4alg/ms4alg.py
ml_ms4alg/ms4alg_spec.py.mp
ml_ms4alg/p_apply_label_map.py
ml_ms4alg/p_create_label_map.py
ml_ms4alg/p_ms4alg.py
ml_ms4alg/version.py
ml_ms4alg-0.3.6.dist-info/METADATA
ml_ms4alg-0.3.6.dist-info/WHEEL
ml_ms4alg-0.3.6.dist-info/top_level.txt
ml_ms4alg-0.3.6.dist-info/RECORD
