Metadata-Version: 2.1
Name: ml-ms4alg
Version: 0.3.6
Summary: Mountainsort v4 for MountainLab
Home-page: https://github.com/magland/ml_ms4alg
Author: Jeremy Magland
Author-email: 
License: UNKNOWN
Platform: UNKNOWN
Classifier: Programming Language :: Python :: 3
Classifier: License :: OSI Approved :: Apache Software License
Classifier: Operating System :: OS Independent
Requires-Dist: dask
Requires-Dist: pybind11
Requires-Dist: isosplit5
Requires-Dist: numpy
Requires-Dist: mountainlab-pytools
Requires-Dist: h5py
Requires-Dist: sklearn
Requires-Dist: spikeextractors (>=0.4.1)
